Metadata-Version: 1.0
Name: mp3play
Version: 0.1.9
Summary: A simple interface for playing music from an MP3 file.
Home-page: http://code.google.com/p/mp3play/
Author: Michael Gundlach
Author-email: gundlach@gmail.com
License: UNKNOWN
Keywords: mp3 api play music audio python module
Platform: UNKNOWN
Classifier: Development Status :: 5 - Production/Stable
Classifier: Environment :: Win32 (MS Windows)
Classifier: Intended Audience :: Developers
Classifier: License :: OSI Approved :: Apache Software License
Classifier: Operating System :: Microsoft :: Windows
Classifier: Programming Language :: Python
Classifier: Topic :: Multimedia :: Sound/Audio
Classifier: Topic :: Software Development :: Libraries :: Python Modules
